strom_gedacht_api_client/__init__.py
strom_gedacht_api_client/api/__init__.py
strom_gedacht_api_client/api/region_states/__init__.py
strom_gedacht_api_client/api/region_states/get_v1_now.py
strom_gedacht_api_client/api/region_states/get_v1_states.py
strom_gedacht_api_client/client.py
strom_gedacht_api_client/errors.py
strom_gedacht_api_client/models/__init__.py
strom_gedacht_api_client/models/region_state.py
strom_gedacht_api_client/models/region_state_now_view_model.py
strom_gedacht_api_client/models/region_state_range_view_model.py
strom_gedacht_api_client/models/region_state_view_model.py
strom_gedacht_api_client/py.typed
strom_gedacht_api_client/types.py
strom_gedacht_api_client-1.dist-info/WHEEL
strom_gedacht_api_client-1.dist-info/METADATA
strom_gedacht_api_client-1.dist-info/RECORD
