Metadata-Version: 2.1
Name: strom-gedacht-api-client
Version: 1
Summary: A client library for accessing StromGedacht API
Author: Jannes Mueller
Requires-Python: >=3.8,<4.0
Classifier: Programming Language :: Python :: 3
Classifier: Programming Language :: Python :: 3.10
Classifier: Programming Language :: Python :: 3.8
Classifier: Programming Language :: Python :: 3.9
Requires-Dist: attrs (>=21.3.0)
Requires-Dist: httpx (>=0.15.4,<0.25.0)
Requires-Dist: python-dateutil (>=2.8.0,<3.0.0)
